tireless/__init__.py
tireless/cli.py
tireless/helper.py
tireless/inputs.py
tireless/loader.py
tireless/tir/page.j2
tireless-0.1.1.dist-info/entry_points.txt
tireless-0.1.1.dist-info/LICENCE.txt
tireless-0.1.1.dist-info/METADATA
tireless-0.1.1.dist-info/WHEEL
tireless-0.1.1.dist-info/RECORD
