Metadata-Version: 2.1
Name: tireless
Version: 0.1.1
Summary: Python web framework built on top of flask to accelerate web development process
License: MIT
Keywords: tireless,flask,package,web-package,Eric Kweyunga,maverickweyunga@gmail.com
Author: Eric_Kweyunga
Author-email: maverickweyunga@gmail.com
Maintainer: Eric_Kweyunga
Maintainer-email: maverickweyunga@gmail.com
Requires-Python: >=3.8,<4.0
Classifier: License :: OSI Approved :: MIT License
Classifier: Programming Language :: Python :: 3
Classifier: Programming Language :: Python :: 3.8
Classifier: Programming Language :: Python :: 3.9
Classifier: Programming Language :: Python :: 3.10
Classifier: Programming Language :: Python :: 3.11
Classifier: Programming Language :: Python :: 3.12
Requires-Dist: click (>=8.1.3,<9.0.0)
Requires-Dist: flask (>=3.0,<4.0)
